LICENSE.txt
README.md
__init__.py
prologix.py
setup.py
tcp.py
telepythic.py
library/__init__.py
library/_cmdline.py
library/agilent86140b.py
library/aq6315.py
library/galil.py
library/hp4395a.py
library/sr770.py
library/tekscope.py
library/tekscope_example.py
telepythic.egg-info/PKG-INFO
telepythic.egg-info/SOURCES.txt
telepythic.egg-info/dependency_links.txt
telepythic.egg-info/top_level.txt