Metadata-Version: 1.0
Name: telepythic
Version: 1.5
Summary: A python library for communicating with test equipment and measurement devices
Home-page: https://bitbucket.org/martijnj/telepythic
Author: Martijn Jasperse
Author-email: m.jasperse@gmail.com
License: BSD
Keywords: GPIB VISA comms test equipment measurement devices
Platform: UNKNOWN
